django_redis_connector/__init__.py
django_redis_connector/redis_connector.py
django_redis_connector-1.0.4.dist-info/METADATA
django_redis_connector-1.0.4.dist-info/WHEEL
django_redis_connector-1.0.4.dist-info/top_level.txt
django_redis_connector-1.0.4.dist-info/RECORD
