Metadata-Version: 2.1
Name: django-redis-connector
Version: 1.0.4
Summary: Django Redis Connector
Home-page: https://github.com/django-xxx/django-redis-connector
Author: Hackathon
Author-email: kimi.huang@brightcells.com
License: UNKNOWN
Keywords: Django Redis Connector
Platform: UNKNOWN
Classifier: Development Status :: 5 - Production/Stable
Classifier: Environment :: Web Environment
Classifier: Framework :: Django
Classifier: Intended Audience :: Developers
Classifier: Programming Language :: Python
Classifier: Topic :: Software Development :: Libraries :: Python Modules
Classifier: Topic :: Office/Business :: Financial :: Spreadsheet
Requires-Dist: redis-extensions
